dypac/__init__.py
dypac/bascpp.py
dypac/dypac.py
dypac/embeddings.py
dypac/masker.py
dypac/tests/__init__.py
dypac/tests/test_bascpp.py
dypac/tests/test_dypac.py
dypac-0.7.1.dist-info/METADATA
dypac-0.7.1.dist-info/WHEEL
dypac-0.7.1.dist-info/top_level.txt
dypac-0.7.1.dist-info/RECORD
