Metadata-Version: 2.1
Name: dypac
Version: 0.7.1
Summary: Dynamic parcel aggregation with clustering
Maintainer: Pierre Bellec
Maintainer-email: pierre.bellec@gmail.com
Project-URL: Bug Reports, https://github.com/courtois-neuromod/dypac/issues
Project-URL: Funding, https://cneuromod.ca
Project-URL: Source, https://github.com/courtois-neuromod/dypac
Classifier: Development Status :: 3 - Alpha
Classifier: Intended Audience :: Developers
Classifier: Topic :: Software Development :: Build Tools
Classifier: License :: OSI Approved :: MIT License
Classifier: Programming Language :: Python :: 3.5
Classifier: Programming Language :: Python :: 3.6
Classifier: Programming Language :: Python :: 3.7
Classifier: Programming Language :: Python :: 3.8
Classifier: Programming Language :: Python :: 3.9
Requires-Python: >=3.5
Requires-Dist: numpy
Requires-Dist: matplotlib
Requires-Dist: sklearn
Requires-Dist: nilearn
Requires-Dist: tqdm
